gemagent/__init__.py
gemagent/agent.py
gemagent/config.py
gemagent/parser.py
gemagent/runner.py
gemagent/stream.py
gemagent/tools.py
gemagent/utils.py
gemagent-0.1.1.dist-info/METADATA
gemagent-0.1.1.dist-info/WHEEL
gemagent-0.1.1.dist-info/top_level.txt
gemagent-0.1.1.dist-info/RECORD
