Metadata-Version: 2.4
Name: gemagent
Version: 0.1.1
Summary: Free Gemini-based tool-using agent SDK.
Author: Rishabh Dubey
License: MIT
Project-URL: Homepage, http://github.com/rishabh3562/gemagent-sdk
Classifier: Programming Language :: Python :: 3.8
Classifier: License :: OSI Approved :: MIT License
Requires-Dist: google-generativeai>=0.2.0
Requires-Dist: python-dotenv>=0.20.0
Requires-Dist: nest_asyncio>=1.5.6
